check_tests_structure/__init__.py
check_tests_structure/__main__.py
check_tests_structure/compare.py
check_tests_structure/config.py
check_tests_structure/lookup.py
check_tests_structure-0.0.1.dist-info/LICENSE
check_tests_structure-0.0.1.dist-info/METADATA
check_tests_structure-0.0.1.dist-info/WHEEL
check_tests_structure-0.0.1.dist-info/entry_points.txt
check_tests_structure-0.0.1.dist-info/top_level.txt
check_tests_structure-0.0.1.dist-info/RECORD
