Metadata-Version: 2.1
Name: check-tests-structure
Version: 0.0.1
Author-email: Leonardo Schwarz <leonardo.schwarz@fgcz.ethz.ch>
License: MIT
License-File: LICENSE
Requires-Dist: cyclopts >=2.9
Requires-Dist: pydantic >=2.9
Requires-Dist: rapidfuzz >=3.10
Provides-Extra: test
Requires-Dist: pytest ; extra == 'test'
Requires-Dist: pytest-mock ; extra == 'test'
Requires-Dist: nox ; extra == 'test'
Requires-Dist: pyfakefs ; extra == 'test'
